Metadata-Version: 2.1
Name: sotaque-brasileiro
Version: 0.1.6
Summary: Sotaque Brasileiro é uma base de dados para estudo de regionalismos brasileiros através da voz.
Home-page: https://github.com/gabriel-milan/sotaque-brasileiro
Author: Gabriel Gazola Milan
Author-email: gabriel.gazola@poli.ufrj.br
License: GPL-3.0
Platform: UNKNOWN
Classifier: Development Status :: 4 - Beta
Classifier: Intended Audience :: Developers
Classifier: Topic :: Software Development :: Libraries :: Python Modules
Classifier: License :: OSI Approved :: GNU General Public License v3 (GPLv3)
Classifier: Programming Language :: Python :: 3
Classifier: Programming Language :: Python :: 3.7
Classifier: Programming Language :: Python :: 3.8
Classifier: Programming Language :: Python :: 3.9
